idim/__init__.py
idim/idim.py
idim/py.typed
idim/support_sequence.py
idim/utils.py
idim-1.0.2.dist-info/METADATA
idim-1.0.2.dist-info/WHEEL
idim-1.0.2.dist-info/RECORD
