Metadata-Version: 2.4
Name: idim
Version: 1.0.2
Summary: A Python Library for Computing the Intrinsic Dimension of Geometric Data Sets.
Author-email: thi <hille@cs.uni-kassel.de>
Requires-Python: >=3.11
Requires-Dist: numpy>=1.25.2
Requires-Dist: tqdm>=4.67.1
